[
  {
    "image": "../src/images/Pushup.jpg",
    "name": "Push up",
    "time": "90s",
    "age": "15-40",
    "details": "This exercise is very help for us. We do it every day and you body is improve day by day. It's help to grow you body healthy."
  },
  {
    "image": "../src/images/Pushup.jpg",
    "name": "Push up",
    "time": "90s",
    "age": "15-40",
    "details": "This exercise is very help for us. We do it every day and you body is improve day by day. It's help to grow you body healthy."
  },
  {
    "image": "../src/images/Pushup.jpg",
    "name": "Push up",
    "time": "90s",
    "age": "15-40",
    "details": "This exercise is very help for us. We do it every day and you body is improve day by day. It's help to grow you body healthy."
  },
  {
    "image": "../src/images/Pushup.jpg",
    "name": "Push up",
    "time": "90s",
    "age": "15-40",
    "details": "This exercise is very help for us. We do it every day and you body is improve day by day. It's help to grow you body healthy."
  },
  {
    "image": "../src/images/Pushup.jpg",
    "name": "Push up",
    "time": "90s",
    "age": "15-40",
    "details": "This exercise is very help for us. We do it every day and you body is improve day by day. It's help to grow you body healthy."
  },
  {
    "image": "../src/images/Pushup.jpg",
    "name": "Push up",
    "time": "90s",
    "age": "15-40",
    "details": "This exercise is very help for us. We do it every day and you body is improve day by day. It's help to grow you body healthy."
  }
]
